mslib/__init__.py
mslib/_modidx.py
mslib/core.py
mslib/data/__init__.py
mslib/data/cmc.py
mslib-0.2.2.dist-info/LICENSE
mslib-0.2.2.dist-info/METADATA
mslib-0.2.2.dist-info/WHEEL
mslib-0.2.2.dist-info/entry_points.txt
mslib-0.2.2.dist-info/top_level.txt
mslib-0.2.2.dist-info/RECORD
