Metadata-Version: 2.1
Name: mslib
Version: 0.2.2
Summary: mslib
Home-page: https://github.com/markusschanta/mslib
Author: Markus Schanta
Author-email: markus@schanta.at
License: Apache Software License 2.0
Keywords: nbdev jupyter notebook python
Classifier: Development Status :: 4 - Beta
Classifier: Intended Audience :: Developers
Classifier: Natural Language :: English
Classifier: Programming Language :: Python :: 3.7
Classifier: Programming Language :: Python :: 3.8
Classifier: Programming Language :: Python :: 3.9
Classifier: Programming Language :: Python :: 3.10
Classifier: License :: OSI Approved :: Apache Software License
Requires-Python: >=3.7
Provides-Extra: dev
License-File: LICENSE
